Metadata-Version: 2.1
Name: mubicry
Version: 0.0.1
Summary: Só Gerador de rotulo, por enquanto
Home-page: 
Author: Fabricio Leal
Author-email: 
License: MIT
Keywords: rotulo
Classifier: Development Status :: 5 - Production/Stable
Classifier: Intended Audience :: Education
Classifier: Operating System :: Microsoft :: Windows :: Windows 10
Classifier: License :: OSI Approved :: MIT License
Classifier: Programming Language :: Python :: 3
License-File: LICENSE.txt
